smartsms_py/__init__.py
smartsms_py/exception.py
smartsms_py/smartsms.py
smartsmspy-1.0.1.dist-info/LICENSE
smartsmspy-1.0.1.dist-info/METADATA
smartsmspy-1.0.1.dist-info/WHEEL
smartsmspy-1.0.1.dist-info/top_level.txt
smartsmspy-1.0.1.dist-info/RECORD
